mpesa_c2b_sdk/__init__.py
mpesa_c2b_sdk/auth.py
mpesa_c2b_sdk/c2b.py
mpesa_c2b_sdk/config.py
mpesa_c2b_sdk-0.1.1.dist-info/licenses/LICENSE
mpesa_c2b_sdk-0.1.1.dist-info/METADATA
mpesa_c2b_sdk-0.1.1.dist-info/WHEEL
mpesa_c2b_sdk-0.1.1.dist-info/top_level.txt
mpesa_c2b_sdk-0.1.1.dist-info/RECORD
